LICENSE.txt
MANIFEST.in
README.md
setup.cfg
setup.py
docs/Package_Info.md
phiml/VERSION
phiml/__init__.py
phiml/_troubleshoot.py
phiml/latent.py
phiml/nn.py
phiml.egg-info/PKG-INFO
phiml.egg-info/SOURCES.txt
phiml.egg-info/dependency_links.txt
phiml.egg-info/requires.txt
phiml.egg-info/top_level.txt
phiml/backend/__init__.py
phiml/backend/_backend.py
phiml/backend/_buffer.py
phiml/backend/_dtype.py
phiml/backend/_linalg.py
phiml/backend/_linalg_preconditioner.py
phiml/backend/_minimize.py
phiml/backend/_numpy_backend.py
phiml/backend/_object.py
phiml/backend/_partition.py
phiml/backend/_profile.py
phiml/backend/_triangular_wip.py
phiml/backend/xops.py
phiml/backend/jax/__init__.py
phiml/backend/jax/_jax_backend.py
phiml/backend/jax/stax_nets.py
phiml/backend/tensorflow/__init__.py
phiml/backend/tensorflow/_compile_cuda.py
phiml/backend/tensorflow/_profiling.py
phiml/backend/tensorflow/_tf_backend.py
phiml/backend/tensorflow/_tf_cuda_resample.py
phiml/backend/tensorflow/nets.py
phiml/backend/torch/__init__.py
phiml/backend/torch/_torch_backend.py
phiml/backend/torch/_torch_hooks.py
phiml/backend/torch/nets.py
phiml/dataclasses/__init__.py
phiml/dataclasses/_dataclasses.py
phiml/dataclasses/_dep.py
phiml/dataclasses/_merge.py
phiml/math/__init__.py
phiml/math/_deprecated.py
phiml/math/_fit.py
phiml/math/_functional.py
phiml/math/_lin_trace.py
phiml/math/_magic_ops.py
phiml/math/_nd.py
phiml/math/_ops.py
phiml/math/_optimize.py
phiml/math/_shape.py
phiml/math/_sparse.py
phiml/math/_tensors.py
phiml/math/_trace.py
phiml/math/_tree.py
phiml/math/_var.py
phiml/math/extrapolation.py
phiml/math/magic.py
phiml/math/perm.py
phiml/os/__init__.py
phiml/os/path.py
phiml/parallel/__init__.py
phiml/parallel/_cls_serialize.py
phiml/parallel/_parallel.py
phiml/parallel/_pgraph.py
phiml/parallel/_tensor_cache.py