Metadata-Version: 2.1
Name: phiml
Version: 1.15.0
Summary: Unified API for machine learning
Home-page: https://github.com/tum-pbs/PhiML
Download-URL: https://github.com/tum-pbs/PhiML/archive/1.15.0.tar.gz
Author: Philipp Holl
Author-email: philipp.holl@tum.de
License: MIT
Keywords: Machine Learning,Deep Learning,Math,Linear systems,Sparse,Tensor,Named dimensions
Classifier: Development Status :: 5 - Production/Stable
Classifier: Intended Audience :: Developers
Classifier: Topic :: Software Development :: Build Tools
Classifier: License :: OSI Approved :: MIT License
Classifier: Programming Language :: Python :: 3
Classifier: Programming Language :: Python :: 3.6
Classifier: Programming Language :: Python :: 3.7
Classifier: Programming Language :: Python :: 3.8
Classifier: Programming Language :: Python :: 3.9
Classifier: Programming Language :: Python :: 3.10
Classifier: Programming Language :: Python :: 3.11
License-File: LICENSE.txt
Requires-Dist: numpy
Requires-Dist: scipy>=1.5.4
Requires-Dist: packaging
Requires-Dist: h5py
